ansi_sgr/__init__.py
ansi_sgr/element.py
ansi_sgr/protocol.py
ansi_sgr/sgr.py
ansi_sgr-0.1.0.dist-info/METADATA
ansi_sgr-0.1.0.dist-info/WHEEL
ansi_sgr-0.1.0.dist-info/top_level.txt
ansi_sgr-0.1.0.dist-info/RECORD
