Metadata-Version: 2.2
Name: ANSI-SGR
Version: 0.1.0
Requires-Python: >=3.10
Requires-Dist: ProtocolMan<0.2,>=0.1
Requires-Dist: wcwidth<0.3,>=0.2
